yabs/__init__.py
yabs/cli.py
yabs/cmd_init.py
yabs/commands.py
yabs/plugin_manager.py
yabs/task_runner.py
yabs/util.py
yabs/version_manager.py
yabs/task/__init__.py
yabs/task/build.py
yabs/task/bump.py
yabs/task/check.py
yabs/task/commit.py
yabs/task/common.py
yabs/task/exec.py
yabs/task/github_release.py
yabs/task/push.py
yabs/task/pypi_release.py
yabs/task/tag.py
yabs/task/winget_release.py
yabs-0.6.1.data/data/CHANGELOG.md
yabs-0.6.1.dist-info/LICENSE.txt
yabs-0.6.1.dist-info/METADATA
yabs-0.6.1.dist-info/WHEEL
yabs-0.6.1.dist-info/entry_points.txt
yabs-0.6.1.dist-info/top_level.txt
yabs-0.6.1.dist-info/RECORD
