Metadata-Version: 2.1
Name: yabs
Version: 0.6.1
Summary: Yet Another Build Script
Home-page: https://github.com/mar10/yabs
Author: Martin Wendt
Author-email: yabs@wwwendt.de
Maintainer: Martin Wendt
Maintainer-email: yabs@wwwendt.de
License: MIT
Project-URL: Bug Tracker, https://github.com/mar10/yabs/issues
Project-URL: Source Code, https://github.com/mar10/yabs
Project-URL: Documentation, https://yabs.readthedocs.io
Project-URL: Download, https://github.com/mar10/yabs/releases/latest
Keywords: build,setup,ci,workflow,automation
Classifier: Development Status :: 4 - Beta
Classifier: Environment :: Console
Classifier: Intended Audience :: Developers
Classifier: License :: OSI Approved :: MIT License
Classifier: Operating System :: OS Independent
Classifier: Programming Language :: Python
Classifier: Programming Language :: Python :: 3
Classifier: Programming Language :: Python :: 3 :: Only
Classifier: Programming Language :: Python :: 3.8
Classifier: Programming Language :: Python :: 3.9
Classifier: Programming Language :: Python :: 3.10
Classifier: Programming Language :: Python :: 3.11
Classifier: Programming Language :: Python :: 3.12
Classifier: Topic :: Software Development :: Build Tools
Classifier: Topic :: System :: Installation/Setup
Classifier: Topic :: System :: Software Distribution
License-File: LICENSE.txt
Requires-Dist: click
Requires-Dist: GitPython
Requires-Dist: jinja2
Requires-Dist: PyGithub
Requires-Dist: PyYAML
Requires-Dist: semantic-version
Requires-Dist: setuptools
Requires-Dist: snazzy
Requires-Dist: toml
Requires-Dist: twine
Requires-Dist: wheel
